cosmica.py
CLI_Cosmica-1.0.dist-info/METADATA
CLI_Cosmica-1.0.dist-info/WHEEL
CLI_Cosmica-1.0.dist-info/entry_points.txt
CLI_Cosmica-1.0.dist-info/top_level.txt
CLI_Cosmica-1.0.dist-info/RECORD
