Metadata-Version: 2.1
Name: CLI-Cosmica
Version: 1.0
Requires-Dist: eel
